ketos/__init__.py
ketos/utils.py
ketos/audio/__init__.py
ketos/audio/annotation.py
ketos/audio/audio_loader.py
ketos/audio/base_audio.py
ketos/audio/spectrogram.py
ketos/audio/waveform.py
ketos/audio/utils/__init__.py
ketos/audio/utils/axis.py
ketos/audio/utils/filter.py
ketos/audio/utils/misc.py
ketos/data_handling/__init__.py
ketos/data_handling/data_feeding.py
ketos/data_handling/data_handling.py
ketos/data_handling/database_interface.py
ketos/data_handling/parsing.py
ketos/data_handling/selection_table.py
ketos/neural_networks/__init__.py
ketos/neural_networks/cnn.py
ketos/neural_networks/densenet.py
ketos/neural_networks/inception.py
ketos/neural_networks/resnet.py
ketos/neural_networks/dev_utils/__init__.py
ketos/neural_networks/dev_utils/detection.py
ketos/neural_networks/dev_utils/losses.py
ketos/neural_networks/dev_utils/nn_interface.py
ketos/tests/__init__.py
ketos/tests/cleanup.py
ketos/tests/conftest.py
ketos/tests/test_utils.py
ketos/tests/audio/__init__.py
ketos/tests/audio/test_annotation.py
ketos/tests/audio/test_audio_loader.py
ketos/tests/audio/test_base_audio.py
ketos/tests/audio/test_spectrogram.py
ketos/tests/audio/test_waveform.py
ketos/tests/audio/utils/__init__.py
ketos/tests/audio/utils/test_axis.py
ketos/tests/audio/utils/test_filter.py
ketos/tests/audio/utils/test_misc.py
ketos/tests/data_handling/__init__.py
ketos/tests/data_handling/test_data_feeding.py
ketos/tests/data_handling/test_data_handling.py
ketos/tests/data_handling/test_database_interface.py
ketos/tests/data_handling/test_parsing.py
ketos/tests/data_handling/test_selection_table.py
ketos/tests/neural_networks/__init__.py
ketos/tests/neural_networks/test_cnn.py
ketos/tests/neural_networks/test_densenet.py
ketos/tests/neural_networks/test_detection.py
ketos/tests/neural_networks/test_inception.py
ketos/tests/neural_networks/test_losses.py
ketos/tests/neural_networks/test_nn_interface.py
ketos/tests/neural_networks/test_resnet.py
ketos-2.1.3.dist-info/LICENSE
ketos-2.1.3.dist-info/METADATA
ketos-2.1.3.dist-info/WHEEL
ketos-2.1.3.dist-info/top_level.txt
ketos-2.1.3.dist-info/RECORD
